tastytrade_api/__init__.py
tastytrade_api/authentication.py
tastytrade_api/symbology.py
tastytrade_api/account/__init__.py
tastytrade_api/account/account_handler.py
tastytrade_api/account/balances_positions.py
tastytrade_api/account/watchlist.py
tastytrade_api/market_data/__init__.py
tastytrade_api/market_data/instruments.py
tastytrade_api/market_data/market_metrics.py
tastytrade_api/streamer/__init__.py
tastytrade_api/streamer/dx_mapping.py
tastytrade_api/streamer/dxfeed_handler.py
tastytrade_api/streamer/streamer.py
tests/__init__.py
tests/test_authentication.py
tastytrade_api-1.1.2.dist-info/LICENSE
tastytrade_api-1.1.2.dist-info/METADATA
tastytrade_api-1.1.2.dist-info/WHEEL
tastytrade_api-1.1.2.dist-info/top_level.txt
tastytrade_api-1.1.2.dist-info/RECORD
