Metadata-Version: 2.1
Name: tastytrade-api
Version: 1.1.2
Summary: A Python client and SDK for the Tastytrade API
Home-page: https://github.com/peter-oroszvari/tastytrade-api
Author: Peter Oroszvari
Author-email: peter@oroszvari.hu
Classifier: Development Status :: 4 - Beta
Classifier: Intended Audience :: Developers
Classifier: License :: OSI Approved :: MIT License
Classifier: Programming Language :: Python :: 3
Classifier: Programming Language :: Python :: 3.6
Classifier: Programming Language :: Python :: 3.7
Classifier: Programming Language :: Python :: 3.8
Classifier: Programming Language :: Python :: 3.9
Classifier: Programming Language :: Python :: 3.10
Requires-Python: >=3.6
License-File: LICENSE
Requires-Dist: requests
Requires-Dist: websocket-client
Requires-Dist: websockets
